xpost/__init__.py
xpost/cli.py
xpost/climod.py
xpost/encrypt.py
xpost/engine.py
xpost-0.1.1.dist-info/LICENSE
xpost-0.1.1.dist-info/METADATA
xpost-0.1.1.dist-info/WHEEL
xpost-0.1.1.dist-info/entry_points.txt
xpost-0.1.1.dist-info/top_level.txt
xpost-0.1.1.dist-info/RECORD
