Metadata-Version: 2.1
Name: xpost
Version: 0.1.1
Summary: A CLI for managing Twitter APIs and Twitter posts.
Home-page: https://github.com/1darshanpatil/xpost
Author: Darshan P.
Author-email: drshnp@outlook.com
License: MIT
Project-URL: Documentation, https://github.com/1darshanpatil/xpost#readme
Project-URL: Source, https://github.com/1darshanpatil/xpost
Project-URL: Tracker, https://github.com/1darshanpatil/xpost/issues
Keywords: twitter,cli,api,tweet,social media
Classifier: Development Status :: 4 - Beta
Classifier: Programming Language :: Python :: 3
Classifier: License :: OSI Approved :: MIT License
Classifier: Operating System :: OS Independent
Requires-Python: >=3.6
License-File: LICENSE
Requires-Dist: tweepy >=3.10.0
Requires-Dist: fire >=0.5.0
Requires-Dist: cryptography >=3.4.7
